LICENSE.rst
MANIFEST.in
README.rst
setup.py
nose_timing.egg-info/PKG-INFO
nose_timing.egg-info/SOURCES.txt
nose_timing.egg-info/dependency_links.txt
nose_timing.egg-info/entry_points.txt
nose_timing.egg-info/not-zip-safe
nose_timing.egg-info/requires.txt
nose_timing.egg-info/top_level.txt
timing/__init__.py
timing/plugins.py