Metadata-Version: 1.0
Name: nose-timing
Version: 0.1.1
Summary: Timing plugin for nose
Home-page: https://github.com/andymckay/nose-timing
Author: Andy McKay
Author-email: andym@mozilla.com
License: BSD
Platform: UNKNOWN
Classifier: Intended Audience :: Developers
Classifier: Natural Language :: English
Classifier: Operating System :: OS Independent
Classifier: Framework :: Django
